{
  "https://jakubiwanowski.dev": "2025-12-27",
  "https://samdking.co.uk": "2025-12-27",
  "https://tannerdolby.com": "2025-12-27",
  "https://amberwilson.co.uk": "2025-12-27",
  "https://chipcullen.com": "2025-12-27",
  "https://chromatichq.com": "2025-12-27",
  "https://frankfuchs.net": "2025-12-27",
  "https://heydonworks.com": "2025-12-27",
  "https://jondueck.ca": "2025-12-27",
  "https://lukeb.co.uk": "2025-12-27",
  "https://nicolashery.com": "2025-12-27",
  "https://tjaddison.com": "2025-12-27",
  "https://bryanlrobinson.com": "2025-12-27",
  "https://fullstackdigital.io": "2025-12-27",
  "https://cfjedimaster.github.io": "2025-12-27",
  "https://lea.codes": "2025-12-27",
  "https://sjhuskey.info": "2025-12-27",
  "https://chrissmith.xyz": "2025-12-27",
  "https://joesahlsa.dev": "2025-12-27",
  "https://moosedog.io": "2025-12-27",
  "https://web.dev": "2025-12-27",
  "https://nealgamradt.com": "2025-12-27",
  "https://morten.dk": "2025-12-27",
  "https://bennypowers.dev": "2025-12-27",
  "https://bigelow.io": "2025-12-27",
  "https://fictivekin.com": "2025-12-27",
  "https://sheetsj.com": "2025-12-27",
  "https://www.statox.fr": "2025-12-27",
  "https://garage.sekrab.com": "2025-12-27",
  "https://www.andberry.me": "2025-12-27",
  "https://www.digitalocean.com": "2025-12-27",
  "https://www.azulcoding.com": "2025-12-27",
  "https://someantics.dev": "2025-12-27",
  "https://bnijenhuis.nl": "2025-12-27",
  "https://www.brianperry.dev": "2025-12-27",
  "https://remotesynthesis.com": "2025-12-27",
  "https://www.algolia.com": "2025-12-27",
  "https://illtron.net": "2025-12-27",
  "https://www.contentful.com": "2025-12-27",
  "https://www.crossingtheruby.com": "2025-12-27",
  "https://www.dandenney.com": "2025-12-27",
  "https://w3things.com": "2025-12-27",
  "https://blog.logrocket.com": "2025-12-27",
  "https://dropinblog.com": "2025-12-27",
  "https://davidea.st": "2025-12-27",
  "https://www.hendricks.rocks": "2025-12-27",
  "https://desmondrivet.com": "2025-12-27",
  "https://tiiny.host": "2025-12-27",
  "https://eevis.codes": "2025-12-27",
  "https://fershad.com": "2025-12-27",
  "https://www.freecodecamp.org": "2025-12-27",
  "https://ghost.org": "2025-12-27",
  "https://henry.codes": "2025-12-27",
  "https://www.halo-lab.com": "2025-12-27",
  "https://github.com": "2025-12-27",
  "https://randomerrors.dev": "2025-12-27",
  "https://simpixelated.com": "2025-12-27",
  "https://sombriks.com.br": "2025-12-27",
  "https://jaydanurw.in": "2025-12-27",
  "https://mtm.dev": "2025-12-27",
  "https://litlab.stanford.edu": "2025-12-27",
  "https://www.mathew-paul.nz": "2025-12-27",
  "https://www.maxkohler.com": "2025-12-27",
  "https://events.lunch.dev": "2025-12-27",
  "https://michelenasti.com": "2025-12-27",
  "https://www.mikeaparicio.com": "2025-12-27",
  "https://mikeneumegen.com": "2025-12-27",
  "https://ramono.me": "2025-12-27",
  "https://rphunt.github.io": "2025-12-27",
  "https://www.falldowngoboone.com": "2025-12-27",
  "https://simonmcmanus.com": "2025-12-27",
  "https://www.stevenhicks.me": "2025-12-27",
  "https://www.tim-kleyersburg.de": "2025-12-27",
  "https://tomichen.com": "2025-12-27",
  "https://webpixels.io": "2025-12-27",
  "https://lostinbrittany.dev": "2025-12-27",
  "https://eystein.no": "2025-12-27",
  "https://squalr.us": "2025-12-27",
  "https://grgml.xyz": "2025-12-27",
  "https://joshghent.com": "2025-12-27",
  "https://dipeshkr.me": "2025-12-27",
  "https://www.codeflood.net": "2025-12-27",
  "https://khalidabuhakmeh.com": "2025-12-27",
  "https://jandewil.de": "2025-12-27",
  "https://piperhaywood.com": "2025-12-27",
  "https://www.ryangittings.co.uk": "2025-12-27",
  "https://www.webiny.com": "2025-12-27",
  "https://nickyt.online": "2025-12-27",
  "https://www.kevinpowell.co": "2025-12-27",
  "https://gittings.studio": "2025-12-27",
  "https://anitacheng.com": "2025-12-27",
  "https://www.jetbrains.com": "2025-12-27",
  "https://blakewatson.com": "2025-12-27",
  "https://samimaatta.fi": "2025-12-27",
  "https://www.lkhrs.com": "2025-12-27",
  "https://www.conor.zone": "2025-12-27",
  "https://stefanzweifel.dev": "2025-12-27",
  "https://keith.is": "2025-12-27",
  "https://www.justus.ws": "2025-12-27",
  "https://jonmircha.com": "2025-12-27",
  "https://ptsefton.com": "2025-12-27",
  "https://robwood.uk": "2025-12-27",
  "https://arnaught.neocities.org": "2025-12-27",
  "https://helenchong.omg.lol": "2025-12-27",
  "https://johnskinnerportfolio.com": "2025-12-27",
  "https://michaelengen.com": "2025-12-27",
  "https://baty.net": "2025-12-27",
  "https://minimo.io": "2025-12-27",
  "https://www.fastmail.com": "2025-12-27",
  "https://sainthood.xyz": "2025-12-27",
  "https://www.hayes.software": "2025-12-27",
  "https://schalkneethling.com": "2025-12-27",
  "https://sandtoken.com": "2025-12-27",
  "https://bkardell.com": "2025-12-27",
  "https://ryan.himmelwright.net": "2025-12-27",
  "https://davidmoll.net": "2025-12-27",
  "https://www.simplethread.com": "2025-12-27",
  "https://tailscale.com": "2025-12-27",
  "https://ldstephens.net": "2025-12-27",
  "https://bryn.codes": "2025-12-27",
  "https://jjoohhnn.com": "2025-12-27",
  "https://tlohde.com": "2025-12-27",
  "https://mwdelaney.me": "2025-12-27",
  "https://rosenqvist.design": "2025-12-27",
  "https://etch.co": "2025-12-27",
  "https://rigotti.nl": "2025-12-27",
  "https://skiles.blue": "2025-12-27",
  "https://aninus.com": "2025-12-27",
  "https://alix.guillard.fr": "2025-12-27",
  "https://withlogic.co": "2025-12-27",
  "https://kajkandler.github.io": "2025-12-27",
  "https://dsriseah.com": "2025-12-27",
  "https://timklapdor.me": "2025-12-27",
  "https://world.optimizely.com": "2025-12-27",
  "https://danurbanowicz.com": "2025-12-28",
  "https://javan.us": "2025-12-28",
  "https://deletetwitter.com": "2025-12-28",
  "https://nostossafari.com": "2025-12-28",
  "https://www.tomroseveare.com": "2025-12-28",
  "https://edukatte.netlify.app": "2025-12-28",
  "https://wilks.co": "2025-12-28",
  "https://tc39.es": "2025-12-28",
  "https://jeromestephan.de": "2025-12-28",
  "https://kevin.gimbel.dev": "2025-12-28",
  "https://angular.pridontetradze.com": "2025-12-28",
  "https://runawayracing.com": "2025-12-28",
  "https://retro-sound.js.org": "2025-12-28",
  "https://doubleshift.rknight.me": "2025-12-28",
  "https://jcmendez.io": "2025-12-28",
  "https://tbrown.org": "2025-12-28",
  "https://dadjokes.claytonerrington.com": "2025-12-28",
  "https://jerseycitybitcoin.com": "2025-12-28",
  "https://www.mattknight.io": "2025-12-28",
  "https://blog.sanketpathak.com": "2025-12-28",
  "https://jarijokinen.com": "2025-12-28",
  "https://a-cuca.github.io": "2025-12-28",
  "https://classic.spaceninja.com": "2025-12-28",
  "https://vandeventures.netlify.app": "2025-12-28",
  "https://yozo.ooo": "2025-12-28",
  "https://raphaellekerbrat.com": "2025-12-28",
  "https://jmhobbs.github.io": "2025-12-28",
  "https://allstageproductions.com": "2025-12-28",
  "https://agiletto.se": "2025-12-28",
  "https://evanstheatre.ca": "2025-12-28",
  "https://tei-c.org": "2025-12-28",
  "https://surajwate.com": "2025-12-28",
  "https://bristolfurs.co.uk": "2025-12-28",
  "https://2024.djangocon.us": "2025-12-28",
  "https://eblu.space": "2025-12-28",
  "https://pagaidu.github.io": "2025-12-28",
  "https://evrowe.com": "2025-12-28",
  "https://htmlforpeople.com": "2025-12-28",
  "https://magpi.netlify.app": "2025-12-28",
  "https://www.moviecast.app": "2025-12-28",
  "https://livres.louvre.fr": "2025-12-28",
  "https://futurescale.com": "2025-12-28",
  "https://danjewett.net": "2025-12-28",
  "https://47-watch.com": "2025-12-28",
  "https://begrant.io": "2025-12-28",
  "https://indiagrant.com": "2025-12-28",
  "https://fossgaming.codeberg.page": "2025-12-28",
  "https://noktorum.com": "2025-12-28",
  "https://liz.hoeser.dev": "2025-12-28",
  "https://18f.org": "2025-12-28",
  "https://byggorebro.se": "2025-12-28",
  "https://techcats.netlify.app": "2025-12-28",
  "https://microsoft.github.io": "2025-12-28",
  "https://annotator.incubator.apache.org": "2025-12-28",
  "https://royale.apache.org": "2025-12-28",
  "https://carlotrimarchi.it": "2025-12-28",
  "https://photos.srgower.com": "2025-12-28",
  "https://emonc.org": "2025-12-28",
  "https://www.nulle-part.fr": "2025-12-28",
  "https://gaiety.me": "2025-12-28",
  "https://roodesign.co.uk": "2025-12-28",
  "https://blog.possiblyaxolotl.com": "2025-12-28",
  "https://347online.me": "2025-12-28",
  "https://urbanflow.art": "2025-12-28",
  "https://inclusivedesign24.org": "2025-12-28",
  "https://ocean.app": "2025-12-28",
  "https://keveney.com": "2025-12-28",
  "https://adamwilbert.com": "2025-12-28",
  "https://www.fiff.de": "2025-12-28",
  "https://api.swordfight.me": "2025-12-28"
}