[
  {
    "Issue": 1,
    "Type": "blog post",
    "Title": "I Finally Understand Eleventy's Data Cascade",
    "Link": "https://benmyers.dev/blog/eleventy-data-cascade/",
    "Date": "2021-02-21",
    "Author": "Ben Myers",
    "Categories": ["Data Cascade", "Global Data"]
  },
  {
    "Issue": 1,
    "Type": "blog post",
    "Title": "Word count and reading time in Eleventy",
    "Link": "https://www.brycewray.com/posts/2022/09/word-count-reading-time-eleventy/",
    "Date": "2022-09-20",
    "Author": "Bryce Wray",
    "Categories": ["How to..."]
  },
  {
    "Issue": 1,
    "Type": "blog post",
    "Title": "Lazy select-based pagination in Eleventy",
    "Link": "https://coryd.dev/posts/2023/lazy-select-based-pagination-eleventy/",
    "Date": "2023-03-27",
    "Author": "Cory Dransfeldt",
    "Categories": ["Pagination"]
  },
  {
    "Issue": 1,
    "Type": "blog post",
    "Title": "Automate and syndicate content from Eleventy to Mastodon",
    "Link": "https://coryd.dev/posts/2023/automate-syndicate-content-mastodon-eleventy/",
    "Date": "2023-03-27",
    "Author": "Cory Dransfeldt",
    "Categories": ["Social Media"]
  },
  {
    "Issue": 1,
    "Type": "blog post",
    "Title": "Building my /now page using Eleventy",
    "Link": "https://coryd.dev/posts/2023/building-my-now-page-using-eleventy/",
    "Date": "2023-03-18",
    "Author": "Cory Dransfeldt",
    "Categories": ["Remote Data", "Now Page"]
  },
  {
    "Issue": 1,
    "Type": "blog post",
    "Title": "Upgrading to Eleventy 2.0.0",
    "Link": "https://danabyerly.com/notes/upgrading-to-eleventy-2-0-0/",
    "Date": "2023-02-26",
    "Author": "Dana Byerly",
    "Categories": ["How to..."]
  },
  {
    "Issue": 1,
    "Type": "blog post",
    "Title": "Easy Date and Time Formatting with Luxon",
    "Link": "https://11tywebcfun.netlify.app/recipes/easy-date-and-time-formatting/",
    "Date": "2023-03-29",
    "Author": "Evan Sheehan",
    "Categories": ["Dates"]
  },
  {
    "Issue": 1,
    "Type": "blog post",
    "Title": "Using WebC for progressively-enhanced UI elements",
    "Link": "https://lewisdale.dev/post/using-webc-for-progressively-enhanced-ui-elements/",
    "Date": "2023-02-23",
    "Author": "Lewis Dale",
    "Categories": ["WebC"]
  },
  {
    "Issue": 1,
    "Type": "blog post",
    "Title": "Quick WebC Tip",
    "Link": "https://www.raymondcamden.com/2023/01/27/quick-webc-tip",
    "Date": "2023-01-27",
    "Author": "Raymond Camden",
    "Categories": ["WebC"]
  },
  {
    "Issue": 1,
    "Type": "blog post",
    "Title": "Using JavaScript in a WebC Component",
    "Link": "https://www.raymondcamden.com/2023/02/03/using-javascript-in-a-webc-component",
    "Date": "2023-02-03",
    "Author": "Raymond Camden",
    "Categories": ["WebC"]
  },
  {
    "Issue": 1,
    "Type": "blog post",
    "Title": "Supporting PDF Embeds in an Eleventy WebC Component",
    "Link": "https://www.raymondcamden.com/2023/03/01/supporting-pdf-embeds-in-an-eleventy-webc-component",
    "Date": "2023-03-01",
    "Author": "Raymond Camden",
    "Categories": ["How to..."]
  },
  {
    "Issue": 1,
    "Type": "blog post",
    "Title": "Adding Webmentions to Your Site",
    "Link": "https://rknight.me/adding-webmentions-to-your-site/",
    "Date": "2023-01-30",
    "Author": "Robb Knight",
    "Categories": ["Webmentions"]
  },
  {
    "Issue": 1,
    "Type": "blog post",
    "Title": "Why I use Eleventy",
    "Link": "https://ryanccn.dev/posts/why-eleventy/",
    "Date": "2022-11-04",
    "Author": "Ryan Cao",
    "Categories": ["Why Eleventy?"]
  },
  {
    "Issue": 1,
    "Type": "blog post",
    "Title": "Extracting and using Critical CSS on my Eleventy site",
    "Link": "https://www.silvestar.codes/articles/extracting-and-using-critical-css-on-my-eleventy-site/",
    "Date": "2023-02-24",
    "Author": "Silvestar Bistrović",
    "Categories": ["CSS/Sass"]
  },
  {
    "Issue": 1,
    "Type": "blog post",
    "Title": "Building A Membership Site With 11ty",
    "Link": "https://11ty.rocks/posts/building-a-membership-site-with-11ty/",
    "Date": "2023-01-26",
    "Author": "Stephanie Eckles",
    "Categories": ["How to...", "Edge Functions"]
  },
  {
    "Issue": 1,
    "Type": "blog post",
    "Title": "Eleventy Collection Schemas",
    "Link": "https://11ty.rocks/posts/eleventy-collection-schemas/",
    "Date": "2023-02-17",
    "Author": "Stephanie Eckles",
    "Categories": ["Collections"]
  },
  {
    "Issue": 1,
    "Type": "blog post",
    "Title": "Smart Incremental Rebuilds With eleventyImport",
    "Link": "https://11ty.rocks/posts/smart-incremental-rebuilds-with-eleventy-import/",
    "Date": "2023-03-18",
    "Author": "Stephanie Eckles",
    "Categories": ["How to..."]
  },
  {
    "Issue": 2,
    "Type": "blog post",
    "Title": "Blogging with Eleventy",
    "Link": "https://logicalcobwebs.com/blog/blogging-with-eleventy/",
    "Date": "2023-03-27",
    "Author": "Bill Horsman",
    "Categories": ["How to...", "Blogging"]
  },
  {
    "Issue": 2,
    "Type": "blog post",
    "Title": "The evolution of my CSS pipeline in Eleventy (part 2)",
    "Link": "https://www.bobmonsour.com/posts/the-evolution-of-my-CSS-pipeline-in-eleventy-part-2/",
    "Date": "2023-03-26",
    "Author": "Bob Monsour",
    "Categories": ["CSS/Sass"]
  },
  {
    "Issue": 2,
    "Type": "blog post",
    "Title": "The evolution of my CSS pipeline in Eleventy (part 1)",
    "Link": "https://www.bobmonsour.com/posts/the-evolution-of-my-CSS-pipeline-in-eleventy-part-1/",
    "Date": "2023-03-14",
    "Author": "Bob Monsour",
    "Categories": ["CSS/Sass"]
  },
  {
    "Issue": 2,
    "Type": "blog post",
    "Title": "Scheduled Eleventy builds on Vercel with cron-triggered GitHub actions",
    "Link": "https://coryd.dev/posts/2023/scheduled-eleventy-builds-cron-github-actions/",
    "Date": "2023-03-19",
    "Author": "Cory Dransfeldt",
    "Categories": ["Deployment", "Scheduling"]
  },
  {
    "Issue": 2,
    "Type": "blog post",
    "Title": "What’s New in Eleventy 2: A Great SSG Just Got Better",
    "Link": "https://www.sitepoint.com/eleventy-2/",
    "Date": "2023-03-21",
    "Author": "Craig Buckler",
    "Categories": ["Why Eleventy?"]
  },
  {
    "Issue": 2,
    "Type": "blog post",
    "Title": "Sass in Eleventy, with versioning",
    "Link": "https://danburzo.ro/eleventy-sass/",
    "Date": "2023-03-01",
    "Author": "Dan Burzo",
    "Categories": ["CSS/Sass"]
  },
  {
    "Issue": 2,
    "Type": "blog post",
    "Title": "Slotted content in Eleventy",
    "Link": "https://danburzo.ro/eleventy-slotted-content/",
    "Date": "2023-02-28",
    "Author": "Dan Burzo",
    "Categories": ["How to..."]
  },
  {
    "Issue": 2,
    "Type": "blog post",
    "Title": "Relational data in Eleventy",
    "Link": "https://danburzo.ro/eleventy-relational-data/",
    "Date": "2022-11-26",
    "Author": "Dan Burzo",
    "Categories": ["Data Cascade"]
  },
  {
    "Issue": 2,
    "Type": "blog post",
    "Title": "From Notion to Eleventy",
    "Link": "https://iamschulz.com/from-notion-to-eleventy/",
    "Date": "2022-11-10",
    "Author": "Daniel Shulz",
    "Categories": ["Remote Data"]
  },
  {
    "Issue": 2,
    "Type": "blog post",
    "Title": "Five Million npm Downloads",
    "Link": "https://www.11ty.dev/blog/five-million/",
    "Date": "2023-03-03",
    "Author": "11ty",
    "Categories": ["YouTube"]
  },
  {
    "Issue": 2,
    "Type": "blog post",
    "Title": "A Beginner's Guide to Eleventy - part two",
    "Link": "https://jakubiwanowski.dev/garden/programming/eleventy-guide-part-two/",
    "Date": "2023-01-20",
    "Author": "Jakub Iwanowski",
    "Categories": ["Getting Started"]
  },
  {
    "Issue": 2,
    "Type": "blog post",
    "Title": "A Beginner's Guide to Eleventy - part one",
    "Link": "https://jakubiwanowski.dev/garden/programming/eleventy-guide-part-one/",
    "Date": "2023-01-09",
    "Author": "Jakub Iwanowski",
    "Categories": ["Getting Started"]
  },
  {
    "Issue": 2,
    "Type": "blog post",
    "Title": "Migrating to Eleventy from AnchorCMS",
    "Link": "https://www.joshvickerson.com/posts/migrating-to-eleventy-from-anchorcms/",
    "Date": "2023-03-24",
    "Author": "Josh Vickerson",
    "Categories": ["Migrating to Eleventy"]
  },
  {
    "Issue": 2,
    "Type": "blog post",
    "Title": "Internationalization with Eleventy 2.0 and Netlify",
    "Link": "https://www.lenesaile.com/en/blog/internationalization-with-eleventy-20-and-netlify/",
    "Date": "2023-02-21",
    "Author": "Lene Saile",
    "Categories": ["Internationalization"]
  },
  {
    "Issue": 2,
    "Type": "blog post",
    "Title": "Syncing Letterboxd Data to Markdown Files",
    "Link": "https://www.markllobrera.com/posts/letterboxd-to-markdown/",
    "Date": "2023-03-22",
    "Author": "Mark Llobrera",
    "Categories": ["Remote Data"]
  },
  {
    "Issue": 2,
    "Type": "blog post",
    "Title": "How I built my own excerpt for Markdown content in Eleventy",
    "Link": "https://nicolas-hoizey.com/articles/2023/03/31/how-i-built-my-own-excerpt-for-markdown-content-in-eleventy/",
    "Date": "2023-03-31",
    "Author": "Nicolas Hoizey",
    "Categories": ["Markdown"]
  },
  {
    "Issue": 2,
    "Type": "blog post",
    "Title": "Awesome Algolia Updates (and some fixes here...)",
    "Link": "https://www.raymondcamden.com/2023/03/30/awesome-algolia-updates-and-some-fixes-here",
    "Date": "2023-03-30",
    "Author": "Raymond Camden",
    "Categories": ["How to..."]
  },
  {
    "Issue": 2,
    "Type": "blog post",
    "Title": "Bringing your Notion database to life with Eleventy",
    "Link": "https://samdking.co.uk/blog/bringing-your-notion-database-to-life-with-eleventy/",
    "Date": "2022-08-25",
    "Author": "Sam D King",
    "Categories": ["Remote Data"]
  },
  {
    "Issue": 2,
    "Type": "blog post",
    "Title": "Spellchecking my blog posts with cSpell",
    "Link": "https://www.uncenter.org/posts/spellchecking-with-eleventy/",
    "Date": "2023-03-23",
    "Author": "uncenter",
    "Categories": ["How to...", "Blogging"]
  },
  {
    "Issue": 2,
    "Type": "blog post",
    "Title": "Using the Airtable API with Eleventy Collections",
    "Link": "https://willdarwin.com/writing/airtable/",
    "Date": "2023-01-25",
    "Author": "Will Darwin",
    "Categories": ["Remote Data", "Collections"]
  },
  {
    "Issue": 3,
    "Type": "blog post",
    "Title": "GitLab CI Pipeline for Eleventy",
    "Link": "https://aarongoldenthal.com/posts/gitlab-ci-pipeline-for-eleventy/",
    "Date": "2023-04-03",
    "Author": "Aaron Goldenthal",
    "Categories": ["Deployment"]
  },
  {
    "Issue": 3,
    "Type": "blog post",
    "Title": "Rebuilding a PHP App using Isomorphic JavaScript with Eleventy & Netlify",
    "Link": "https://www.aaron-gustafson.com/notebook/rebuilding-a-php-app-using-isomorphic-javascript-with-eleventy-and-netlify/",
    "Date": "2023-02-03",
    "Author": "Aaron Gustafson",
    "Categories": ["Edge Functions", "Netlify"]
  },
  {
    "Issue": 3,
    "Type": "blog post",
    "Title": "Adding a Stripe cart to a static Eleventy website with LiveState: Part 1",
    "Link": "https://launchscout.com/blog/add-stripe-cart-to-eleventy-with-livestate",
    "Date": "2022-11-09",
    "Author": "Chris Nelson",
    "Categories": ["How to..."]
  },
  {
    "Issue": 3,
    "Type": "blog post",
    "Title": "How I Learned to Stop Worrying and Love the Jamstack",
    "Link": "https://daniel-saunders.com/posts/essays/how-i-learned-to-stop-worrying-and-love-the-jamstack/",
    "Date": "2022-09-26",
    "Author": "Daniel Saunders",
    "Categories": ["Why Eleventy?"]
  },
  {
    "Issue": 3,
    "Type": "blog post",
    "Title": "Using Airtable as a Jamstack CMS",
    "Link": "https://daniel-saunders.com/posts/notes/using-airtable-as-a-jamstack-cms/",
    "Date": "2022-12-03",
    "Author": "Daniel Saunders",
    "Categories": ["Remote Data"]
  },
  {
    "Issue": 3,
    "Type": "blog post",
    "Title": "How Stable is Eleventy? (YouTube)",
    "Link": "https://www.youtube.com/watch?v=bPtQmsjXMuo",
    "Date": "2023-04-06",
    "Author": "11ty",
    "Categories": ["YouTube"]
  },
  {
    "Issue": 3,
    "Type": "blog post",
    "Title": "Rebuilding 11ty on a schedule",
    "Link": "https://jamesdoc.com/blog/2023/11ty-daily-rebuilds/",
    "Date": "2023-02-10",
    "Author": "James Doc",
    "Categories": ["Deployment", "Scheduling"]
  },
  {
    "Issue": 3,
    "Type": "blog post",
    "Title": "Moving from WordPress to 11ty",
    "Link": "https://velvetcache.org/2023/04/05/moving-from-wordpress-to-11ty/",
    "Date": "2023-04-05",
    "Author": "John Hobbs",
    "Categories": ["Migrating to Eleventy"]
  },
  {
    "Issue": 3,
    "Type": "blog post",
    "Title": "Eleventy: Building an Image Gallery with CSS Grid and PhotoSwipe",
    "Link": "https://www.markllobrera.com/posts/eleventy-building-image-gallery-photoswipe/",
    "Date": "2023-01-22",
    "Author": "Mark Llobrera",
    "Categories": ["Images", "Image Galleries"]
  },
  {
    "Issue": 3,
    "Type": "blog post",
    "Title": "Eleventy 2.0 & WebC",
    "Link": "https://martinhicks.net/articles/eleventy-and-webc",
    "Date": "2022-12-17",
    "Author": "Martin Hicks",
    "Categories": ["WebC"]
  },
  {
    "Issue": 3,
    "Type": "blog post",
    "Title": "Builder.io's Partytown with 11ty",
    "Link": "https://syntackle.live/blog/builder-io-s-partytown-with-11ty-lN6X2w/",
    "Date": "2023-04-05",
    "Author": "Murtuzaali Surti",
    "Categories": ["How to..."]
  },
  {
    "Issue": 3,
    "Type": "blog post",
    "Title": "Working with CloudCannon and Eleventy - My Experience",
    "Link": "https://www.raymondcamden.com/2023/04/06/working-with-cloudcannon-and-eleventy-my-experience",
    "Date": "2023-04-06",
    "Author": "Raymond Camden",
    "Categories": ["CMS"]
  },
  {
    "Issue": 3,
    "Type": "blog post",
    "Title": "WebC Updates in Eleventy - Looping",
    "Link": "https://www.raymondcamden.com/2023/04/04/webc-updates-in-eleventy-looping",
    "Date": "2023-04-04",
    "Author": "Raymond Camden",
    "Categories": ["WebC"]
  },
  {
    "Issue": 3,
    "Type": "blog post",
    "Title": "A WebC-focused YouTube playlist",
    "Link": "https://www.youtube.com/playlist?list=PLxloNMIFIg7VUcMt3QJC-b-Ly5eZZoUoE",
    "Date": "2023-04-07",
    "Author": "Ricky de Laveaga",
    "Categories": ["YouTube"]
  },
  {
    "Issue": 3,
    "Type": "blog post",
    "Title": "A Step-by-Step Guide to Sorting Eleventy Global Data Files by Date",
    "Link": "https://stevenwoodson.com/blog/a-step-by-step-guide-to-sorting-eleventy-global-data-files-by-date/",
    "Date": "2023-02-02",
    "Author": "Steven Woodson",
    "Categories": ["How to..."]
  },
  {
    "Issue": 3,
    "Type": "blog post",
    "Title": "Adding a Table of Contents to dynamic content in 11ty",
    "Link": "https://stevenwoodson.com/blog/adding-a-table-of-contents-to-dynamic-content-in-11ty/",
    "Date": "2023-02-12",
    "Author": "Steven Woodson",
    "Categories": ["How to..."]
  },
  {
    "Issue": 3,
    "Type": "blog post",
    "Title": "Make Eleventy the next thing you learn",
    "Link": "https://helloyes.dev/blog/2021/elventy-should-be-next/",
    "Date": "2021-09-22",
    "Author": "Thomas Semmler",
    "Categories": ["Getting Started"]
  },
  {
    "Issue": 3,
    "Type": "blog post",
    "Title": "CSS and JavaScript as first-class citizens in Eleventy",
    "Link": "https://pepelsbey.dev/articles/eleventy-css-js/",
    "Date": "2022-11-25",
    "Author": "Vadim Makeev",
    "Categories": ["CSS/Sass"]
  },
  {
    "Issue": 3,
    "Type": "blog post",
    "Title": "3 Methods for scoped styles in web components that work everywhere",
    "Link": "https://www.zachleat.com/web/styling-web-components/",
    "Date": "2023-04-06",
    "Author": "Zach Leatherman",
    "Categories": ["CSS/Sass", "WebC"]
  },
  {
    "Issue": 4,
    "Type": "blog post",
    "Title": "Webmention Setup for Eleventy",
    "Link": "https://chrisburnell.com/article/webmention-eleventy-setup/",
    "Date": "2022-08-25",
    "Author": "Chris Burnell",
    "Categories": ["Webmentions"]
  },
  {
    "Issue": 4,
    "Type": "blog post",
    "Title": "Group posts by year in Eleventy",
    "Link": "https://darekkay.com/blog/eleventy-group-posts-by-year/",
    "Date": "2021-01-31",
    "Author": "Darek Kay",
    "Categories": ["Dates", "How to...", "Collections"]
  },
  {
    "Issue": 4,
    "Type": "blog post",
    "Title": "Includes and Macros",
    "Link": "https://darthmall.net/weblog/2021/includes-and-macros/",
    "Date": "2021-11-20",
    "Author": "Evan Sheehan",
    "Categories": ["Nunjucks/Macros"]
  },
  {
    "Issue": 4,
    "Type": "blog post",
    "Title": "Basic custom taxonomies with Eleventy",
    "Link": "https://www.webstoemp.com/blog/basic-custom-taxonomies-with-eleventy/",
    "Date": "2020-03-04",
    "Author": "Jérôme Coupé",
    "Categories": ["Collections"]
  },
  {
    "Issue": 4,
    "Type": "blog post",
    "Title": "Modular code with Nunjucks and Eleventy",
    "Link": "https://www.webstoemp.com/blog/modular-code-nunjucks-eleventy/",
    "Date": "2021-08-06",
    "Author": "Jérôme Coupé",
    "Categories": ["Nunjucks/Macros"]
  },
  {
    "Issue": 4,
    "Type": "blog post",
    "Title": "Eleventy Custom Content Type Collections and Layouts",
    "Link": "https://www.joshcanhelp.com/eleventy-custom-content-type-collections/",
    "Date": "2022-01-04",
    "Author": "Josh Cunningham",
    "Categories": ["Collections", "Layouts"]
  },
  {
    "Issue": 4,
    "Type": "blog post",
    "Title": "How I built Around the Web",
    "Link": "https://www.ovl.design/text/how-i-built-around-the-web/",
    "Date": "2022-03-15",
    "Author": "Oscar",
    "Categories": ["How to..."]
  },
  {
    "Issue": 4,
    "Type": "blog post",
    "Title": "Static Site Generation with Eleventy (YouTube)",
    "Link": "https://www.youtube.com/watch?v=JiC9JWRsfcE",
    "Date": "2022-09-26",
    "Author": "Shawn Wildermuth",
    "Categories": ["YouTube"]
  },
  {
    "Issue": 4,
    "Type": "blog post",
    "Title": "Process CSS or Sass With LightningCSS",
    "Link": "https://11ty.rocks/posts/process-css-with-lightningcss/",
    "Date": "2023-02-25",
    "Author": "Stephanie Eckles",
    "Categories": ["CSS/Sass"]
  },
  {
    "Issue": 4,
    "Type": "blog post",
    "Title": "A Deep Dive Into Eleventy Static Site Generator",
    "Link": "https://11ty.rocks/posts/deep-dive-eleventy-static-site-generator/",
    "Date": "2021-03-24",
    "Author": "Stephanie Eckles",
    "Categories": ["Getting Started"]
  },
  {
    "Issue": 4,
    "Type": "blog post",
    "Title": "Create a Custom Collection with Eleventy",
    "Link": "https://tannerdolby.com/writing/create-a-custom-collection-with-eleventy/",
    "Date": "2020-10-31",
    "Author": "Tanner Dolby",
    "Categories": ["Collections"]
  }
]
